quickpay_api_client/__init__.py
quickpay_api_client/api.py
quickpay_api_client/client.py
quickpay_api_client/exceptions.py
quickpay_api_client-2.0.0.dist-info/LICENCE.txt
quickpay_api_client-2.0.0.dist-info/METADATA
quickpay_api_client-2.0.0.dist-info/WHEEL
quickpay_api_client-2.0.0.dist-info/top_level.txt
quickpay_api_client-2.0.0.dist-info/RECORD
