Metadata-Version: 2.1
Name: quickpay-api-client
Version: 2.0.0
Summary: Python client for QuickPay API
Home-page: https://github.com/QuickPay/quickpay-python-client
Author: QuickPay Developers
Author-email: support@quickpay.net
License: MIT
Platform: UNKNOWN
Requires-Dist: requests (>=2.5)
